{"cameraMode":{"drawMode":0,"name":"Shaded","section":"Shading Mode"},"sceneLighting":true,"audioPlay":false,"sceneViewState":{"showFog":true,"showMaterialUpdate":false,"showSkybox":true,"showFlares":true,"showImageEffects":true,"showParticleSystems":true},"in2DMode":false,"pivot":{"x":252.82386779785157,"y":231.09632873535157,"z":-61.918853759765628},"rotation":{"x":-0.14308524131774903,"y":-0.4262576401233673,"z":0.06850463896989823,"w":-0.8905938863754273},"size":3.3495876789093019,"orthographic":false}